vault_redirector/__init__.py
vault_redirector/redirector.py
vault_redirector/runner.py
vault_redirector/version.py
vault_redirector/tests/__init__.py
vault_redirector/tests/requester.py
vault_redirector/tests/test_redirector.py
vault_redirector/tests/test_runner.py
vault_redirector/tests/test_version.py
vault_redirector/tests/testdata.py
vault_redirector-0.2.0.dist-info/DESCRIPTION.rst
vault_redirector-0.2.0.dist-info/METADATA
vault_redirector-0.2.0.dist-info/RECORD
vault_redirector-0.2.0.dist-info/WHEEL
vault_redirector-0.2.0.dist-info/entry_points.txt
vault_redirector-0.2.0.dist-info/metadata.json
vault_redirector-0.2.0.dist-info/top_level.txt
