Metadata-Version: 2.0
Name: vault-redirector
Version: 0.2.0
Summary: Python/Twisted application to redirect Hashicorp Vault client requests to the active node in a HA cluster
Home-page: https://github.com/manheim/vault-redirector-twisted
Author: Manheim
Author-email: tooling@manheim.com
License: UNKNOWN
Keywords: hashicorp vault vaultproject
Platform: UNKNOWN
Classifier: Development Status :: 4 - Beta
Classifier: Environment :: Console
Classifier: Environment :: No Input/Output (Daemon)
Classifier: Environment :: Web Environment
Classifier: Framework :: Twisted
Classifier: Intended Audience :: Information Technology
Classifier: License :: OSI Approved :: MIT License
Classifier: Natural Language :: English
Classifier: Operating System :: OS Independent
Classifier: Programming Language :: Python
Classifier: Programming Language :: Python :: 2
Classifier: Programming Language :: Python :: 2.7
Classifier: Programming Language :: Python :: 3
Classifier: Programming Language :: Python :: 3.3
Classifier: Programming Language :: Python :: 3.4
Classifier: Programming Language :: Python :: 3.5
Classifier: Topic :: Internet
Classifier: Topic :: Internet :: WWW/HTTP
Classifier: Topic :: Security
Classifier: Topic :: System :: Networking
Classifier: Topic :: Utilities
Requires-Dist: requests
Requires-Dist: twisted (>=16.0.0)
Provides-Extra: tls
Requires-Dist: pem; extra == 'tls'
Requires-Dist: pyOpenSSL; extra == 'tls'
